README.rst
setup.cfg
setup.py
zped.py
zped.egg-info/PKG-INFO
zped.egg-info/SOURCES.txt
zped.egg-info/dependency_links.txt
zped.egg-info/top_level.txt