Metadata-Version: 1.1
Name: zped
Version: 0.1.2
Summary: A poorly-architected event dispatcher that does magic and lets you do terrible things
Home-page: https://github.com/zoidbb/zped
Author: Ber Zoidberg
Author-email: ber@zoidplex.net
License: UNKNOWN
Keywords: event dispatcher
Platform: UNKNOWN
Classifier: Development Status :: 3 - Alpha
Classifier: Intended Audience :: Developers
Classifier: License :: OSI Approved :: BSD License
Classifier: Programming Language :: Python :: 2.7
Classifier: Programming Language :: Python :: 3.3
